mishtar/__init__.py
mishtar/chunked.py
mishtar/mynamed.py
mishtar/mynumber.py
mishtar/myplace.py
mishtar/mytemped.old.2.py
mishtar/mytemped.old.py
mishtar/mytemped.py
mishtar/mytemped_const.old.2.py
mishtar/mytemped_const.old.py
mishtar/mytemped_const.py
mishtar/place_const.py
mishtar-0.1.dist-info/DESCRIPTION.rst
mishtar-0.1.dist-info/METADATA
mishtar-0.1.dist-info/RECORD
mishtar-0.1.dist-info/WHEEL
mishtar-0.1.dist-info/metadata.json
mishtar-0.1.dist-info/top_level.txt
