Metadata-Version: 2.0
Name: mishtar
Version: 0.1
Summary: Mishtar: Arabic text chuncker, temporal and named entities extraction
Home-page: http://pypi.python.com/projects/mishtar/
Author: Taha Zerrouki
Author-email: taha_zerrouki@hotmail.com
License: GPL
Platform: UNKNOWN
Classifier: Development Status :: 5 - Production/Stable
Classifier: Natural Language :: Arabic
Classifier: Intended Audience :: Developers
Classifier: Operating System :: OS Independent
Classifier: Programming Language :: Python
Classifier: Topic :: Text Processing :: Linguistic
Requires-Dist: pyarabic (>=0.6.2)
